[
  {
    "id": "5394e38a1abe4fc2babfccf8b215ef82",
    "title": "《新闻联播》 20260516 2100",
    "url": "https://tv.cctv.cn/2026/05/16/VIDE6MQho985eesQe9j9t0Th260516.shtml",
    "date": "2026-05-16",
    "broadcastTime": "21:00",
    "image": "https://p4.img.cctvpic.com/fmspic/2026/05/16/5394e38a1abe4fc2babfccf8b215ef82-1.jpg",
    "description": "本期节目主要内容：\n1.《求是》杂志发表习近平总书记重要文章《做强做优做大实体经济》；\n2.应习近平邀请 俄罗斯总统将对华进行国事访问；\n3.【凝心聚力 真抓实干 奋力实现“十五五”良好开局】青海立足资源禀赋 推进绿色算电协同发展 宁夏持续加力 筑牢西北地区重要生态安全屏障；\n4.神舟二十三号船箭组合体转运至发射区 计划近日择机发射；\n5.一季度末普惠型小微企业贷款余额同比增长9.9%；\n6.【在希望的田野上】我国夏油作物收获进入高峰；\n7.南水北调已累计向北方调水880亿立方米；\n8.我国工业资源循环利用提速升级；\n9.我国储能产业发展势头强劲；\n10.以旧换新 持续激发消费活力；\n11.我国将全面推行家庭病床服务；\n12.大范围降雨持续 各地全力做好强降雨防范应对工作；\n13.国内联播快讯：\n（1）平陆运河航运枢纽主体工程建设完成；\n（2）我国所有城市将全面开展城市体检；\n（3）《2026年知识产权强国建设推进计划》印发；\n（4）第二艘国产大型邮轮“爱达·花城号”出海试航；\n（5）中国科学院第二十二届公众科学日活动举办；\n14.黎以停火延长45天 以军持续袭击黎南部；\n15.伊朗称为外交谈判争取机会 以色列称正准备重启对伊朗军事行动；\n16.国际联播快讯：\n（1）美经济界预测美二季度通胀水平大幅提升；\n（2）刚果（金）暴发埃博拉疫情 已致80人死亡；\n（3）泰国曼谷火车与巴士相撞 已造成8死多伤；\n（4）欧盟机构称欧洲成为全球变暖最快大陆。\n（《新闻联播》 20260516 21:00）",
    "program": "xwlb",
    "guid": "5394e38a1abe4fc2babfccf8b215ef82",
    "sourcePageUrl": "https://tv.cctv.cn/2026/05/16/VIDE6MQho985eesQe9j9t0Th260516.shtml",
    "streamUrl": "https://dhls.cntv.cdn20.com/asp/audio/5/3/9/4/5394e38a1abe4fc2babfccf8b215ef82/mp3/main.m3u8",
    "type": "m3u8",
    "fallback": false,
    "hlsUrl": "https://dhls.cntv.cdn20.com/asp/audio/5/3/9/4/5394e38a1abe4fc2babfccf8b215ef82/mp3/main.m3u8",
    "audioSourceUrl": "https://dhls.cntv.cdn20.com/asp/audio/5/3/9/4/5394e38a1abe4fc2babfccf8b215ef82/mp3/main.m3u8",
    "createdAt": "2026-05-17T10:02:12.730Z",
    "durationSeconds": 1799.56
  },
  {
    "id": "9913e90fc83d4bb19558d4992fdddcc7",
    "title": "《新闻联播》 20260515 2100",
    "url": "https://tv.cctv.cn/2026/05/15/VIDEAs0XdoNVdkpFCA93Htz8260515.shtml",
    "date": "2026-05-15",
    "broadcastTime": "21:00",
    "image": "https://p5.img.cctvpic.com/photoAlbum/vms/standard/img/2026/5/15/VIDEzIBsdw0a6tx77gG16zxd260515.jpg",
    "description": "本期节目主要内容：\r\n1.习近平同美国总统在中南海小范围会晤；\r\n2.李强主持召开国务院常务会议；\r\n3.赵乐际在贵州调研；\r\n4.【“十五五”开好局起好步】江苏奋力在推进中国式现代化中走在前做示范 奋力谱写中国式现代化安徽篇章；\r\n5.【在希望的田野上】西南麦区迎来大面积收获；\r\n6.一季度我国数字产业收入同比增长12.9%；\r\n7.1至4月全国铁路发送旅客15.55亿人次；\r\n8.国务院新闻办举行“新征程上的奋斗者”中外记者见面会；\r\n9.国内联播快讯：\r\n（1）中央宣传部 全国妇联联合发布2026年“最美家庭”；\r\n（2）我国新修订《药品管理法实施条例》今天正式施行；\r\n（3）力箭系列运载火箭完成百星发射；\r\n（4）中央财政两年投入10亿元支持校园足球发展；\r\n（5）上海深化政务服务“一网通办”改革 累计办件量已超8亿件；\r\n（6）“2026世界市长对话·成都”活动举行；\r\n（7）广州港南沙港区五期工程开工；\r\n（8）雄安新区举办首场青年人才交流会；\r\n（9）首届中国新文创市集暨潮玩游园会在京举办；\r\n10.多国人士表示中美元首会谈为两国关系提供战略指引 为全球注入稳定性；\r\n11.国际媒体高度关注中美元首会谈；\r\n12.国际联播快讯：\r\n（1）以黎在美举行新一轮会谈 分歧明显；\r\n（2）也门政府与胡塞武装达成人员释放协议；\r\n（3）印度恶劣天气致超百人死亡；\r\n（4）美基拉韦厄火山喷出大量岩浆。\r\n（《新闻联播》 20260515 21:00）",
    "program": "xwlb",
    "guid": "9913e90fc83d4bb19558d4992fdddcc7",
    "sourcePageUrl": "https://tv.cctv.cn/2026/05/15/VIDEAs0XdoNVdkpFCA93Htz8260515.shtml",
    "streamUrl": "https://dhls.cntv.cdn20.com/asp/audio/9/9/1/3/9913e90fc83d4bb19558d4992fdddcc7/mp3/main.m3u8",
    "type": "m3u8",
    "fallback": false,
    "hlsUrl": "https://dhls.cntv.cdn20.com/asp/audio/9/9/1/3/9913e90fc83d4bb19558d4992fdddcc7/mp3/main.m3u8",
    "audioSourceUrl": "https://dhls.cntv.cdn20.com/asp/audio/9/9/1/3/9913e90fc83d4bb19558d4992fdddcc7/mp3/main.m3u8",
    "createdAt": "2026-05-16T09:52:58.613Z",
    "durationSeconds": 1799.4
  },
  {
    "id": "d5e519dbad2a43ea92da61dfb267ab96",
    "title": "《新闻联播》 20260514 2100",
    "url": "https://tv.cctv.cn/2026/05/14/VIDEr0Mtz3C4E5WIYDH68D9f260514.shtml",
    "date": "2026-05-14",
    "broadcastTime": "21:00",
    "image": "https://p2.img.cctvpic.com/photoAlbum/vms/standard/img/2026/5/14/VIDEH13Att69Wlb2RnBk8Z6y260514.jpg",
    "description": "本期节目主要内容：\r\n1.习近平举行仪式欢迎美国总统访华；\r\n2.习近平同美国总统会谈；\r\n3.习近平同美国总统参观天坛；\r\n4.习近平为美国总统举行欢迎宴会；\r\n5.李强会见美国工商界代表；\r\n6.4月末我国社会融资规模存量同比增长7.8%；\r\n7.4月份我国电商物流运行稳中有升；\r\n8.一季度工程机械产品出口保持快速增长；\r\n9.夏粮旺季收购即将启动 预计收购小麦1亿吨左右；\r\n10.国务院新闻办举行“新征程上的奋斗者”中外记者见面会；\r\n11.国内联播快讯：\r\n（1）2025年我国城市再生水利用量突破220亿立方米；\r\n（2）1—4月全国期货市场累计成交额同比增长42.75%；\r\n（3）2026年度国家医保基金飞行检查全面启动；\r\n（4）“数据要素×”今年首场数据场景供需对接会今天举办；\r\n（5）朱雀二号改进型遥五运载火箭发射成功；\r\n12.国际社会高度关注中美元首会谈；\r\n13.以军袭击黎南部多地 以称在所有战区创造“新的安全现实”；\r\n14.国际联播快讯：\r\n（1）欧佩克下调2026年全球石油需求增长预期；\r\n（2）欧盟一季度进口俄液化天然气创近年新高；\r\n（3）日本破产企业数连续5个月同比增加；\r\n（4）英国一邮轮发生诺如病毒感染事件。\r\n（《新闻联播》 20260514 21:00）",
    "program": "xwlb",
    "guid": "d5e519dbad2a43ea92da61dfb267ab96",
    "sourcePageUrl": "https://tv.cctv.cn/2026/05/14/VIDEr0Mtz3C4E5WIYDH68D9f260514.shtml",
    "streamUrl": "https://dhls.cntv.cdn20.com/asp/audio/d/5/e/5/d5e519dbad2a43ea92da61dfb267ab96/mp3/main.m3u8",
    "type": "m3u8",
    "fallback": false,
    "hlsUrl": "https://dhls.cntv.cdn20.com/asp/audio/d/5/e/5/d5e519dbad2a43ea92da61dfb267ab96/mp3/main.m3u8",
    "audioSourceUrl": "https://dhls.cntv.cdn20.com/asp/audio/d/5/e/5/d5e519dbad2a43ea92da61dfb267ab96/mp3/main.m3u8",
    "createdAt": "2026-05-15T10:40:18.866Z",
    "durationSeconds": 1799.64
  },
  {
    "id": "281a2fa69dca4cfa8255206b5d1bba96",
    "title": "《新闻联播》 20260513 2100",
    "url": "https://tv.cctv.cn/2026/05/13/VIDEMUoPmzSvMAJ2YBUgofLM260513.shtml",
    "date": "2026-05-13",
    "broadcastTime": "21:00",
    "image": "https://p4.img.cctvpic.com/fmspic/2026/05/13/281a2fa69dca4cfa8255206b5d1bba96-1.jpg",
    "description": "本期节目主要内容：\n1.【新思想引领新征程】推进国际科技创新中心建设 打造世界级科技创新策源地；\n2.【“十五五”开好局起好步】奋力谱写中国式现代化建设四川新篇章 接续奋斗 开创云南发展新局面；\n3.中美在韩国举行经贸磋商；\n4.一季度全国新设经营主体509.8万户；\n5.外资加速布局中国服务业；\n6.一季度我国水电清洁能源基地建设全面提速；\n7.前4个月全国铁路完成固定资产投资2008亿元；\n8.2025年我国新发现大中型矿产地200处；\n9.全国春灌已全面展开；\n10.多元化文旅场景赋能入境游提质扩容；\n11.国务院新闻办举行“新征程上的奋斗者”中外记者见面会；\n12.国内联播快讯：\n（1）我国2025年药品注册申报和审结数量均创历史新高；\n（2）2025年全国林草种苗质量抽检情况公布；\n（3）“义新欧”中欧班列前4个月出口增长超20%；\n（4）四川盆地发现超深层千亿方级页岩气田；\n（5）引江济淮工程阶段验收工作全面完成；\n（6）2026电影票房突破140亿元；\n13.国际社会期待中美元首会晤引领中美关系平稳前行 惠及世界；\n14.日本民众集会抗议高市政权“扩军”修宪等危险动向；\n15.国际联播快讯：\n（1）黎总统指责以袭击破坏缓和局势努力；\n（2）英工党内部就首相去留分歧严重；\n（3）日本10年期国债收益率升至近30年新高。\n（《新闻联播》 20260513 21:00）",
    "program": "xwlb",
    "guid": "281a2fa69dca4cfa8255206b5d1bba96",
    "sourcePageUrl": "https://tv.cctv.cn/2026/05/13/VIDEMUoPmzSvMAJ2YBUgofLM260513.shtml",
    "streamUrl": "https://dhls.cntv.cdn20.com/asp/audio/2/8/1/a/281a2fa69dca4cfa8255206b5d1bba96/mp3/main.m3u8",
    "type": "m3u8",
    "fallback": false,
    "hlsUrl": "https://dhls.cntv.cdn20.com/asp/audio/2/8/1/a/281a2fa69dca4cfa8255206b5d1bba96/mp3/main.m3u8",
    "audioSourceUrl": "https://dhls.cntv.cdn20.com/asp/audio/2/8/1/a/281a2fa69dca4cfa8255206b5d1bba96/mp3/main.m3u8",
    "createdAt": "2026-05-13T15:52:32.044Z",
    "durationSeconds": 1799.16
  },
  {
    "id": "1351b96c0a474332b22120e00d017047",
    "title": "《新闻联播》 20260512 2100",
    "url": "https://tv.cctv.cn/2026/05/12/VIDEsAbPAUFSpzUyG3RYBi0C260512.shtml",
    "date": "2026-05-12",
    "broadcastTime": "21:00",
    "image": "https://p4.img.cctvpic.com/photoAlbum/vms/standard/img/2026/5/12/VIDE7MrMyZlvrgPxUUh9yy4R260512.jpg",
    "description": "本期节目主要内容：\r\n1.习近平举行仪式欢迎塔吉克斯坦总统访华；\r\n2.习近平同塔吉克斯坦总统会谈；\r\n3.习近平会见文莱王储；\r\n4.习近平会见联合国教科文组织总干事；\r\n5.李强会见塔吉克斯坦总统；\r\n6.李强致电祝贺毛焦尔就任匈牙利总理；\r\n7.赵乐际会见塔吉克斯坦总统；\r\n8.韩正同文莱王储举行会谈；\r\n9.今年以来我国未来产业布局提速；\r\n10.我国农村供水保障水平显著提升；\r\n11.各地各部门开展防灾减灾科普教育活动；\r\n12.国内联播快讯：\r\n（1）我国护士队伍持续壮大 专业素质稳步提升；\r\n（2）2026世界数字教育大会发布八项重要成果；\r\n（3）中央网信办全面部署推进规范短视频内容标注工作；\r\n（4）今年前4个月全国食品贸易进出口同比增长6.5%；\r\n（5）《纺织服装卓越品牌培育行动方案（2026—2028年）》印发；\r\n（6）2026年全国家庭教育宣传周活动启动；\r\n（7）西十高铁全线拉通试验启动；\r\n（8）东北最长跨海大桥主线钢栈桥首段合龙；\r\n13.国际社会高度关注中美元首会晤 期待两国合作为世界注入更多稳定性；\r\n14.国际联播快讯：\r\n（1）伊朗呼吁美国接受其方案；\r\n（2）黎称以军袭击黎南部多地 致7人死亡；\r\n（3）德乌将研发无人机 俄称阻碍局势调解；\r\n（4）日本实际家庭消费连续4个月同比下滑。\r\n（《新闻联播》 20260512 21:00）",
    "program": "xwlb",
    "guid": "1351b96c0a474332b22120e00d017047",
    "sourcePageUrl": "https://tv.cctv.cn/2026/05/12/VIDEsAbPAUFSpzUyG3RYBi0C260512.shtml",
    "streamUrl": "https://dhlsaliwx01.v.cntv.cn/asp/audio/1/3/5/1/1351b96c0a474332b22120e00d017047/mp3/main.m3u8",
    "type": "m3u8",
    "fallback": false,
    "hlsUrl": "https://dhlsaliwx01.v.cntv.cn/asp/audio/1/3/5/1/1351b96c0a474332b22120e00d017047/mp3/main.m3u8",
    "audioSourceUrl": "https://dhlsaliwx01.v.cntv.cn/asp/audio/1/3/5/1/1351b96c0a474332b22120e00d017047/mp3/main.m3u8",
    "createdAt": "2026-05-13T09:23:43.135Z",
    "durationSeconds": 1799.8
  }
]
